reddit_bot/reply_bot.py
reddit_bot/__init__.py
reddit_bot/mail_bot.py
reddit_bot/config.json.template
reddit_bot/main.py
reddit_bot/base.py
reddit_bot-0.2.1.dist-info/DESCRIPTION.rst
reddit_bot-0.2.1.dist-info/top_level.txt
reddit_bot-0.2.1.dist-info/RECORD
reddit_bot-0.2.1.dist-info/entry_points.txt
reddit_bot-0.2.1.dist-info/METADATA
reddit_bot-0.2.1.dist-info/WHEEL
reddit_bot-0.2.1.dist-info/metadata.json
